mkdocs_rich_argparse/__init__.py
mkdocs_rich_argparse/py.typed
mkdocs_rich_argparse-0.1.2.dist-info/licenses/LICENSE
mkdocs_rich_argparse-0.1.2.dist-info/licenses/NOTICE
mkdocs_rich_argparse-0.1.2.dist-info/METADATA
mkdocs_rich_argparse-0.1.2.dist-info/WHEEL
mkdocs_rich_argparse-0.1.2.dist-info/entry_points.txt
mkdocs_rich_argparse-0.1.2.dist-info/top_level.txt
mkdocs_rich_argparse-0.1.2.dist-info/RECORD
