Metadata-Version: 2.4
Name: mkdocs-rich-argparse
Version: 0.1.2
Summary: An MkDocs plugin to generate documentation for a rich argparse parser
Author-email: Stefan Verhoeven <s.verhoeven@esciencecenter.nl>
License:                                  Apache License
Project-URL: Repository, https://github.com/i-VRESSE/mkdocs_rich_argparse
Project-URL: Issues, https://github.com/i-VRESSE/mkdocs_rich_argparse/issues
Keywords: argparse,mkdocs,mkdocs-plugin,rich
Classifier: Development Status :: 2 - Pre-Alpha
Classifier: Intended Audience :: Developers
Classifier: Intended Audience :: Science/Research
Classifier: License :: OSI Approved :: Apache Software License
Classifier: Natural Language :: English
Classifier: Programming Language :: Python :: 3
Classifier: Programming Language :: Python :: 3.10
Classifier: Programming Language :: Python :: 3.11
Classifier: Programming Language :: Python :: 3.12
Classifier: Programming Language :: Python :: 3.13
Requires-Python: >=3.10
License-File: LICENSE
License-File: NOTICE
Requires-Dist: mkdocs>=1.6.1
Requires-Dist: rich>=14.1.0
Requires-Dist: rich-argparse>=1.7.1
Dynamic: license-file
